PackageAvadhut/__init__.py
packageavadhutlad-0.1.dist-info/METADATA
packageavadhutlad-0.1.dist-info/WHEEL
packageavadhutlad-0.1.dist-info/top_level.txt
packageavadhutlad-0.1.dist-info/RECORD
