Metadata-Version: 2.1
Name: packageavadhutlad
Version: 0.1
Summary: This is code for my package
Author: Avadhut Lad
